{
  "type": "Feature",
  "properties": {
    "iso:country":"IS",
    "name:deu_x_preferred":[
        "Fagurh\u00f3lsm\u00fdri"
    ],
    "name:eng_x_preferred":[
        "Fagurh\u00f3lsm\u00fdri"
    ],
    "name:fra_x_preferred":[
        "Fagurh\u00f3lsm\u00fdri"
    ],
    "name:isl_x_preferred":[
        "Fagurh\u00f3lsm\u00fdri"
    ],
    "name:nld_x_preferred":[
        "Fagurh\u00f3lsm\u00fdri"
    ],
    "name:pol_x_preferred":[
        "Fagurh\u00f3lsm\u00fdri"
    ],
    "name:urd_x_preferred":[
        "\u0641\u0627\u06af\u0648\u0631\u06c1\u0648\u0644\u0633\u0645\u00fd\u0631\u06cc"
    ],
    "qs_pg:aaroncc":"IS",
    "qs_pg:name":"Fagurholsmyri",
    "qs_pg:name_adm0":"\u00cdsland",
    "qs_pg:name_adm1":"Auster-Skaftafellssysla",
    "qs_pg:photos":336,
    "qs_pg:photos_1k":68,
    "qs_pg:photos_9k":1,
    "qs_pg:photos_9r":5,
    "qs_pg:photos_all":336,
    "qs_pg:photos_sr":5,
    "qs_pg:pop_sr":0,
    "qs_pg:qs_pg_placetype":"locality",
    "qs_pg:qs_pg_placetype_gp":"Town",
    "qs_pg:woe_adm0":23424845,
    "woe:adm0_id":23424845,
    "woe:name_adm0":"\u00cdsland",
    "woe:name_adm1":"Auster-Skaftafellssysla",
    "woe:placetype":"Town",
    "wof:name":"Fagurholsmyri",
    "wof:placetype":"locality"
},
  "geometry": {"coordinates":[-16.6570755,63.9075195],"type":"Point"}
}