{
  "type": "Feature",
  "properties": {
    "gn:admin1_code":"38.0",
    "gn:admin2_code":"7620",
    "gn:asciiname":"Fellabaer",
    "gn:country_code":"IS",
    "gn:dem":39,
    "gn:feature_class":"P",
    "gn:feature_code":"PPL",
    "gn:name":"Fellabaer",
    "gn:population":403,
    "gn:timezone":"Atlantic/Reykjavik",
    "iso:country":"IS",
    "name:ceb_x_preferred":[
        "Fellabaer"
    ],
    "name:ces_x_preferred":[
        "Fellab\u00e6r"
    ],
    "name:deu_x_preferred":[
        "Fellab\u00e6r"
    ],
    "name:eng_x_preferred":[
        "Fellabaer"
    ],
    "name:fra_x_preferred":[
        "Fellab\u00e6r"
    ],
    "name:isl_x_preferred":[
        "Fellab\u00e6r"
    ],
    "name:isl_x_variant":[
        "Fellab\u00e6",
        "Fellab\u00e6jar"
    ],
    "name:nld_x_preferred":[
        "Fellab\u00e6r"
    ],
    "name:pol_x_preferred":[
        "Fellab\u00e6r"
    ],
    "name:spa_x_preferred":[
        "Fellab\u00e6r"
    ],
    "name:swe_x_preferred":[
        "Fellab\u00e6r"
    ],
    "wof:name":"Fellabaer",
    "wof:placetype":"locality",
    "wof:population":403
},
  "geometry": {"coordinates":[-14.42621,65.28418000000001],"type":"Point"}
}