{
  "type": "Feature",
  "properties": {
    "iso:country":"IS",
    "name:eng_x_preferred":[
        "Hlidar"
    ],
    "name:isl_x_preferred":[
        "Hl\u00ed\u00f0ar"
    ],
    "wof:name":"Hlidar",
    "wof:placetype":"neighbourhood"
},
  "geometry": {"coordinates":[-21.90882837006373,64.13238283101596],"type":"Point"}
}