{
  "type": "Feature",
  "properties": {
    "gn:gn_country":"IS",
    "gn:gn_fcode":"ADMD",
    "gn:gn_pop":0,
    "iso:country":"IS",
    "name:isl_x_preferred":[
        "Reykjanesb\u00e6r"
    ],
    "qs_pg:aaroncc":"IS",
    "qs_pg:gn_country":"IS",
    "qs_pg:gn_fcode":"ADMD",
    "qs_pg:gn_pop":0,
    "qs_pg:name":"Reykjanesb\u00e6r",
    "qs_pg:photos_9r":0,
    "qs_pg:photos_sr":0,
    "qs_pg:pop_sr":0,
    "qs_pg:qs_pg_placetype":"localadmin",
    "wof:name":"Reykjanesb\u00e6r",
    "wof:placetype":"localadmin"
},
  "geometry": {"coordinates":[-22.66667,63.91667],"type":"Point"}
}