{
  "type": "Feature",
  "properties": {
    "iso:country":"IS",
    "name:eng_x_preferred":[
        "Hamrar"
    ],
    "name:isl_x_preferred":[
        "Hamrar"
    ],
    "wof:name":"Hamrar",
    "wof:placetype":"neighbourhood"
},
  "geometry": {"coordinates":[-21.81558714523426,64.1391683742652],"type":"Point"}
}