{
  "type": "Feature",
  "properties": {
    "iso:country":"IS",
    "qs_pg:aaroncc":"IS",
    "qs_pg:name":"Nor\u00ffurfj\u00f6r\u00ffur",
    "qs_pg:name_adm0":"\u00cdsland",
    "qs_pg:name_adm1":"Strandasysla",
    "qs_pg:photos":310,
    "qs_pg:photos_1k":63,
    "qs_pg:photos_9k":1,
    "qs_pg:photos_9r":5,
    "qs_pg:photos_all":310,
    "qs_pg:photos_sr":5,
    "qs_pg:pop_sr":0,
    "qs_pg:qs_pg_placetype":"locality",
    "qs_pg:qs_pg_placetype_gp":"Town",
    "qs_pg:woe_adm0":23424845,
    "woe:adm0_id":23424845,
    "woe:name_adm0":"\u00cdsland",
    "woe:name_adm1":"Strandasysla",
    "woe:placetype":"Town",
    "wof:name":"Nor\u00ffurfj\u00f6r\u00ffur",
    "wof:placetype":"locality"
},
  "geometry": {"coordinates":[-21.557407,66.050162],"type":"Point"}
}