{
  "type": "Feature",
  "properties": {
    "iso:country":"IS",
    "name:eng_x_preferred":[
        "Kringla"
    ],
    "name:isl_x_preferred":[
        "Kringla"
    ],
    "wof:name":"Kringla",
    "wof:placetype":"neighbourhood"
},
  "geometry": {"coordinates":[-21.89547009779729,64.12825696079],"type":"Point"}
}