{
  "type": "Feature",
  "properties": {
    "gn:admin1_code":"38.0",
    "gn:admin2_code":"7617",
    "gn:asciiname":"Starmyri",
    "gn:country_code":"IS",
    "gn:dem":10,
    "gn:feature_class":"P",
    "gn:feature_code":"PPL",
    "gn:name":"Starm\u00fdri",
    "gn:population":0,
    "gn:timezone":"Atlantic/Reykjavik",
    "iso:country":"IS",
    "wof:name":"Starmyri",
    "wof:placetype":"locality"
},
  "geometry": {"coordinates":[-14.55989,64.52752],"type":"Point"}
}