{
  "type": "Feature",
  "properties": {
    "iso:country":"IS",
    "name:eng_x_preferred":[
        "Midbaer"
    ],
    "name:isl_x_preferred":[
        "Mi\u00f0b\u00e6r"
    ],
    "wof:name":"Midbaer",
    "wof:placetype":"neighbourhood"
},
  "geometry": {"coordinates":[-21.94067157151052,64.14756359169554],"type":"Point"}
}