{
  "type": "Feature",
  "properties": {
    "gn:admin1_code":"41.0",
    "gn:admin2_code":"5508",
    "gn:asciiname":"Laekjamot",
    "gn:country_code":"IS",
    "gn:dem":39,
    "gn:feature_class":"P",
    "gn:feature_code":"PPL",
    "gn:name":"L\u00e6kjam\u00f3t",
    "gn:population":0,
    "gn:timezone":"Atlantic/Reykjavik",
    "iso:country":"IS",
    "wof:name":"Laekjamot",
    "wof:placetype":"locality"
},
  "geometry": {"coordinates":[-20.601,65.41859000000001],"type":"Point"}
}