{
  "type": "Feature",
  "properties": {
    "gn:country":"IS",
    "gn:fcode":"ADMD",
    "gn:population":0,
    "iso:country":"IS",
    "label:eng_x_preferred_placetype":[
        "municipality"
    ],
    "label:fra_x_preferred_placetype":[
        "commune"
    ],
    "name:und_x_variant":[
        "\u00d3lafsfj\u00f6r\u00f0ur"
    ],
    "qs_pg:aaroncc":"IS",
    "qs_pg:gn_country":"IS",
    "qs_pg:gn_fcode":"ADMD",
    "qs_pg:gn_pop":0,
    "qs_pg:name":"\u00d3lafsfjar\u00f0arb\u00e6r",
    "qs_pg:photos_9r":0,
    "qs_pg:photos_sr":0,
    "qs_pg:pop_sr":0,
    "qs_pg:qs_pg_placetype":"localadmin",
    "wof:name":"\u00d3lafsfjar\u00f0arb\u00e6r",
    "wof:placetype":"localadmin"
},
  "geometry": {"coordinates":[-18.75,66.08333],"type":"Point"}
}