{
  "type": "Feature",
  "properties": {
    "iso:country":"IS",
    "name:eng_x_preferred":[
        "Hagar"
    ],
    "name:isl_x_preferred":[
        "Hagar"
    ],
    "wof:name":"Hagar",
    "wof:placetype":"neighbourhood"
},
  "geometry": {"coordinates":[-21.95984043491513,64.140233189976],"type":"Point"}
}