{
  "type": "Feature",
  "properties": {
    "gn:admin1_code":"38.0",
    "gn:admin2_code":"7708",
    "gn:asciiname":"Kalfafellsstadur",
    "gn:country_code":"IS",
    "gn:dem":17,
    "gn:feature_class":"P",
    "gn:feature_code":"PPL",
    "gn:name":"K\u00e1lfafellssta\u00f0ur",
    "gn:population":0,
    "gn:timezone":"Atlantic/Reykjavik",
    "iso:country":"IS",
    "wof:name":"Kalfafellsstadur",
    "wof:placetype":"locality"
},
  "geometry": {"coordinates":[-15.87524,64.18209],"type":"Point"}
}