{
  "type": "Feature",
  "properties": {
    "iso:country":"IS",
    "name:eng_x_preferred":[
        "Bryggjuhverfi"
    ],
    "name:isl_x_preferred":[
        "Bryggjuhverfi"
    ],
    "wof:name":"Bryggjuhverfi",
    "wof:placetype":"neighbourhood"
},
  "geometry": {"coordinates":[-21.81821928767191,64.13247860558833],"type":"Point"}
}