{
  "type": "Feature",
  "properties": {
    "gn:admin1_code":"45.0",
    "gn:admin2_code":"3714",
    "gn:asciiname":"Budir",
    "gn:country_code":"IS",
    "gn:dem":1,
    "gn:feature_class":"P",
    "gn:feature_code":"PPLL",
    "gn:name":"B\u00fa\u00f0ir",
    "gn:population":0,
    "gn:timezone":"Atlantic/Reykjavik",
    "iso:country":"IS",
    "name:deu_x_preferred":[
        "B\u00fa\u00f0ir"
    ],
    "name:isl_x_preferred":[
        "B\u00fa\u00f0ir"
    ],
    "name:pol_x_preferred":[
        "B\u00fa\u00f0ir"
    ],
    "name:ukr_x_preferred":[
        "\u0411\u0443\u0434\u0456\u0440"
    ],
    "wof:name":"Budir",
    "wof:placetype":"locality"
},
  "geometry": {"coordinates":[-23.38431,64.82285],"type":"Point"}
}