{
  "type": "Feature",
  "properties": {
    "gn:gn_country":"IS",
    "gn:gn_fcode":"PPL",
    "gn:gn_pop":0,
    "iso:country":"IS",
    "qs_pg:aaroncc":"IS",
    "qs_pg:gn_country":"IS",
    "qs_pg:gn_fcode":"PPL",
    "qs_pg:gn_pop":0,
    "qs_pg:name":"Saurb\u00e6r",
    "qs_pg:name_adm0":"\u00cdsland",
    "qs_pg:name_adm1":"Kjosarsysla",
    "qs_pg:photos":243,
    "qs_pg:photos_1k":49,
    "qs_pg:photos_9k":1,
    "qs_pg:photos_9r":4,
    "qs_pg:photos_all":243,
    "qs_pg:photos_sr":4,
    "qs_pg:pop_sr":0,
    "qs_pg:qs_pg_placetype":"locality",
    "qs_pg:qs_pg_placetype_gp":"Town",
    "qs_pg:woe_adm0":23424845,
    "woe:adm0_id":23424845,
    "woe:name_adm0":"\u00cdsland",
    "woe:name_adm1":"Kjosarsysla",
    "woe:placetype":"Town",
    "wof:name":"Saurb\u00e6r",
    "wof:placetype":"locality"
},
  "geometry": {"coordinates":[-21.83269,64.28398],"type":"Point"}
}