{
  "type": "Feature",
  "properties": {
    "iso:country":"IS",
    "name:eng_x_preferred":[
        "Nordurmyri"
    ],
    "name:isl_x_preferred":[
        "Nor\u00f0urm\u00fdri"
    ],
    "wof:name":"Nordurmyri",
    "wof:placetype":"neighbourhood"
},
  "geometry": {"coordinates":[-21.91878473493659,64.13902270490392],"type":"Point"}
}