{
  "type": "Feature",
  "properties": {
    "iso:country":"IS",
    "qs_pg:aaroncc":"IS",
    "qs_pg:name":"Hrappstadhakot",
    "qs_pg:name_adm0":"\u00cdsland",
    "qs_pg:name_adm1":"Eyjafjardarsysla",
    "qs_pg:photos":153,
    "qs_pg:photos_1k":31,
    "qs_pg:photos_9k":1,
    "qs_pg:photos_9r":4,
    "qs_pg:photos_all":153,
    "qs_pg:photos_sr":4,
    "qs_pg:pop_sr":0,
    "qs_pg:qs_pg_placetype":"locality",
    "qs_pg:qs_pg_placetype_gp":"Town",
    "qs_pg:woe_adm0":23424845,
    "woe:adm0_id":23424845,
    "woe:name_adm0":"\u00cdsland",
    "woe:name_adm1":"Eyjafjardarsysla",
    "woe:placetype":"Town",
    "wof:name":"Hrappstadhakot",
    "wof:placetype":"locality"
},
  "geometry": {"coordinates":[-18.550243,65.957943],"type":"Point"}
}