{
  "type": "Feature",
  "properties": {
    "gn:gn_country":"IS",
    "gn:gn_fcode":"PPL",
    "gn:gn_pop":299,
    "gn:population":262,
    "iso:country":"IS",
    "name:ara_x_preferred":[
        "\u062b\u0646\u063a\u064a\u0631\u064a"
    ],
    "name:cze_x_preferred":[
        "\u00deingeyri"
    ],
    "name:dut_x_preferred":[
        "\u00deingeyri"
    ],
    "name:eng_x_preferred":[
        "Pingeyri"
    ],
    "name:eng_x_variant":[
        "Thingeyri"
    ],
    "name:fre_x_preferred":[
        "\u00deingeyri"
    ],
    "name:ger_x_preferred":[
        "\u00deingeyri"
    ],
    "name:ice_x_preferred":[
        "\u00deingeyri"
    ],
    "name:isl_x_preferred":[
        "\u00deingeyri"
    ],
    "name:isl_x_variant":[
        "\u00deingeyrar"
    ],
    "name:jpn_x_preferred":[
        "\u30b7\u30f3\u30af\u30a8\u30a4\u30ea"
    ],
    "name:pol_x_preferred":[
        "\u00deingeyri"
    ],
    "name:spa_x_preferred":[
        "\u00deingeyri"
    ],
    "name:swe_x_preferred":[
        "\u00deingeyri"
    ],
    "name:unk_x_variant":[
        "D\u00fdrafj\u00f6r\u00f0ur"
    ],
    "qs_pg:aaroncc":"IS",
    "qs_pg:gn_country":"IS",
    "qs_pg:gn_fcode":"PPL",
    "qs_pg:gn_pop":299,
    "qs_pg:name":"Thingeyri",
    "qs_pg:name_adm0":"\u00cdsland",
    "qs_pg:name_adm1":"Vestur-Isafjardarsysla",
    "qs_pg:photos":282,
    "qs_pg:photos_1k":57,
    "qs_pg:photos_9k":1,
    "qs_pg:photos_9r":4,
    "qs_pg:photos_all":282,
    "qs_pg:photos_sr":5,
    "qs_pg:pop_sr":2,
    "qs_pg:qs_pg_placetype":"locality",
    "qs_pg:qs_pg_placetype_gp":"Town",
    "qs_pg:woe_adm0":23424845,
    "woe:adm0_id":23424845,
    "woe:name_adm0":"\u00cdsland",
    "woe:name_adm1":"Vestur-Isafjardarsysla",
    "woe:placetype":"Town",
    "wof:name":"Thingeyri",
    "wof:placetype":"locality",
    "wof:population":262
},
  "geometry": {"coordinates":[-23.48882,65.88281000000001],"type":"Point"}
}