{
  "type": "Feature",
  "properties": {
    "gn:gn_country":"IS",
    "gn:gn_fcode":"ADMD",
    "gn:gn_pop":0,
    "iso:country":"IS",
    "name:unk_x_variant":[
        "Borgarhreppur"
    ],
    "qs_pg:aaroncc":"IS",
    "qs_pg:gn_country":"IS",
    "qs_pg:gn_fcode":"ADMD",
    "qs_pg:gn_pop":0,
    "qs_pg:name":"Borgarbygg\u00f0",
    "qs_pg:photos_9r":0,
    "qs_pg:photos_sr":0,
    "qs_pg:pop_sr":0,
    "qs_pg:qs_pg_placetype":"localadmin",
    "wof:name":"Borgarbygg\u00f0",
    "wof:placetype":"localadmin"
},
  "geometry": {"coordinates":[-21.85,64.65000000000001],"type":"Point"}
}