{
  "type": "Feature",
  "properties": {
    "gn:country":"IS",
    "gn:fcode":"ADMD",
    "gn:population":0,
    "iso:country":"IS",
    "label:eng_x_preferred_placetype":[
        "municipality"
    ],
    "label:fra_x_preferred_placetype":[
        "commune"
    ],
    "name:ceb_x_preferred":[
        "Borgarbygg\u00f0"
    ],
    "name:deu_x_preferred":[
        "Borgarbygg\u00f0"
    ],
    "name:eus_x_preferred":[
        "Borgarbygg\u00f0"
    ],
    "name:fin_x_preferred":[
        "Borgarbygg\u00f0"
    ],
    "name:fra_x_preferred":[
        "Borgarbygg\u00f0"
    ],
    "name:isl_x_preferred":[
        "Borgarbygg\u00f0"
    ],
    "name:ita_x_preferred":[
        "Borgarbygg\u00f0"
    ],
    "name:nld_x_preferred":[
        "Borgarbygg\u00f0"
    ],
    "name:nor_x_preferred":[
        "Borgarbygg\u00f0"
    ],
    "name:pol_x_preferred":[
        "Borgarbygg\u00f0"
    ],
    "name:rus_x_preferred":[
        "\u0411\u043e\u0440\u0433\u0430\u0440\u0431\u0438\u0433\u0434"
    ],
    "name:sme_x_preferred":[
        "Borgarbygg\u00f0"
    ],
    "name:spa_x_preferred":[
        "Borgarbygg\u00f0"
    ],
    "name:sqi_x_preferred":[
        "Borgarbyggd"
    ],
    "name:swe_x_preferred":[
        "Borgarbygg\u00f0"
    ],
    "name:ukr_x_preferred":[
        "\u0411\u043e\u0440\u0433\u0430\u0440\u0431\u0456\u0433\u0434"
    ],
    "name:und_x_variant":[
        "Borgarhreppur"
    ],
    "qs_pg:aaroncc":"IS",
    "qs_pg:gn_country":"IS",
    "qs_pg:gn_fcode":"ADMD",
    "qs_pg:gn_pop":0,
    "qs_pg:name":"Borgarbygg\u00f0",
    "qs_pg:photos_9r":0,
    "qs_pg:photos_sr":0,
    "qs_pg:pop_sr":0,
    "qs_pg:qs_pg_placetype":"localadmin",
    "wof:name":"Borgarbygg\u00f0",
    "wof:placetype":"localadmin"
},
  "geometry": {"coordinates":[-21.85,64.65000000000001],"type":"Point"}
}