{
  "type": "Feature",
  "properties": {
    "gn:gn_country":"IS",
    "gn:gn_fcode":"PPL",
    "gn:gn_pop":0,
    "iso:country":"IS",
    "name:isl_x_preferred":[
        "Horn"
    ],
    "qs_pg:aaroncc":"IS",
    "qs_pg:gn_country":"IS",
    "qs_pg:gn_fcode":"PPL",
    "qs_pg:gn_pop":0,
    "qs_pg:name":"Horn",
    "qs_pg:name_adm0":"\u00cdsland",
    "qs_pg:name_adm1":"Nordur-Isafjardarsysla",
    "qs_pg:photos":192,
    "qs_pg:photos_1k":39,
    "qs_pg:photos_9k":1,
    "qs_pg:photos_9r":4,
    "qs_pg:photos_all":192,
    "qs_pg:photos_sr":4,
    "qs_pg:pop_sr":3,
    "qs_pg:qs_pg_placetype":"locality",
    "qs_pg:qs_pg_placetype_gp":"Town",
    "qs_pg:woe_adm0":23424845,
    "woe:adm0_id":23424845,
    "woe:name_adm0":"\u00cdsland",
    "woe:name_adm1":"Nordur-Isafjardarsysla",
    "woe:placetype":"Town",
    "wof:name":"Horn",
    "wof:placetype":"locality"
},
  "geometry": {"coordinates":[-22.45212,66.45201],"type":"Point"}
}