{
  "type": "Feature",
  "properties": {
    "gn:gn_country":"IS",
    "gn:gn_fcode":"PPL",
    "gn:gn_pop":0,
    "iso:country":"IS",
    "name:bos_x_preferred":[
        "Horn"
    ],
    "name:bre_x_preferred":[
        "Horn"
    ],
    "name:bul_x_preferred":[
        "\u0425\u043e\u0440\u043d"
    ],
    "name:ceb_x_preferred":[
        "Horn"
    ],
    "name:ces_x_preferred":[
        "Horn"
    ],
    "name:dan_x_preferred":[
        "Horn"
    ],
    "name:deu_x_preferred":[
        "Horn"
    ],
    "name:ell_x_preferred":[
        "\u03a7\u03bf\u03c1\u03bd"
    ],
    "name:epo_x_preferred":[
        "Horn"
    ],
    "name:eus_x_preferred":[
        "Horn"
    ],
    "name:fas_x_preferred":[
        "\u0634\u0627\u062e"
    ],
    "name:fin_x_preferred":[
        "Horn"
    ],
    "name:fra_x_preferred":[
        "Horn"
    ],
    "name:heb_x_preferred":[
        "\u05d4\u05d5\u05e8\u05df"
    ],
    "name:isl_x_preferred":[
        "Horn"
    ],
    "name:ita_x_preferred":[
        "Horn"
    ],
    "name:jpn_x_preferred":[
        "\u30db\u30fc\u30f3"
    ],
    "name:lit_x_preferred":[
        "Hornas"
    ],
    "name:nld_x_preferred":[
        "Horn"
    ],
    "name:nor_x_preferred":[
        "Horn"
    ],
    "name:pol_x_preferred":[
        "Horn"
    ],
    "name:por_x_preferred":[
        "Horn"
    ],
    "name:rus_x_preferred":[
        "\u0425\u043e\u0440\u043d"
    ],
    "name:sco_x_preferred":[
        "Horn"
    ],
    "name:slk_x_preferred":[
        "Horn"
    ],
    "name:swe_x_preferred":[
        "Horn"
    ],
    "name:vol_x_preferred":[
        "Horn"
    ],
    "qs_pg:aaroncc":"IS",
    "qs_pg:gn_country":"IS",
    "qs_pg:gn_fcode":"PPL",
    "qs_pg:gn_pop":0,
    "qs_pg:name":"Horn",
    "qs_pg:name_adm0":"\u00cdsland",
    "qs_pg:name_adm1":"Nordur-Isafjardarsysla",
    "qs_pg:photos":192,
    "qs_pg:photos_1k":39,
    "qs_pg:photos_9k":1,
    "qs_pg:photos_9r":4,
    "qs_pg:photos_all":192,
    "qs_pg:photos_sr":4,
    "qs_pg:pop_sr":3,
    "qs_pg:qs_pg_placetype":"locality",
    "qs_pg:qs_pg_placetype_gp":"Town",
    "qs_pg:woe_adm0":23424845,
    "woe:adm0_id":23424845,
    "woe:name_adm0":"\u00cdsland",
    "woe:name_adm1":"Nordur-Isafjardarsysla",
    "woe:placetype":"Town",
    "wof:name":"Horn",
    "wof:placetype":"locality"
},
  "geometry": {"coordinates":[-22.45212,66.45201],"type":"Point"}
}