{
  "type": "Feature",
  "properties": {
    "gn:gn_country":"IS",
    "gn:gn_fcode":"PPL",
    "gn:gn_pop":1262,
    "gn:population":1489,
    "iso:country":"IS",
    "name:alb_x_preferred":[
        "\u00deorl\u00e1ksh\u00f6fn"
    ],
    "name:baq_x_preferred":[
        "\u00deorl\u00e1ksh\u00f6fn"
    ],
    "name:bel_x_preferred":[
        "\u0413\u043e\u0440\u0430\u0434 \u0422\u0430\u0440\u043b\u0430\u045e\u043a\u0441\u0445\u0451\u0431\u043d"
    ],
    "name:chi_x_preferred":[
        "\u7d22\u52de\u514b\u65af\u8d6b\u672c"
    ],
    "name:cze_x_preferred":[
        "\u00deorl\u00e1ksh\u00f6fn"
    ],
    "name:dut_x_preferred":[
        "\u00deorl\u00e1ksh\u00f6fn"
    ],
    "name:eng_x_preferred":[
        "Thorlakshofn"
    ],
    "name:fin_x_preferred":[
        "\u00deorl\u00e1ksh\u00f6fn"
    ],
    "name:fre_x_preferred":[
        "Thorlaksh\u00f6fn"
    ],
    "name:geo_x_preferred":[
        "\u10e2\u10dd\u10e0\u10da\u10d0\u10d9\u10e1\u10e8\u10d8\u10dd\u10d1\u10dc\u10d8"
    ],
    "name:ger_x_preferred":[
        "\u00deorl\u00e1ksh\u00f6fn"
    ],
    "name:ice_x_preferred":[
        "\u00deorl\u00e1ksh\u00f6fn"
    ],
    "name:ind_x_preferred":[
        "\u00deorl\u00e1ksh\u00f6fn"
    ],
    "name:isl_x_preferred":[
        "\u00deorl\u00e1ksh\u00f6fn"
    ],
    "name:isl_x_variant":[
        "\u00deorl\u00e1kshafnar"
    ],
    "name:jpn_x_preferred":[
        "\u30bd\u30eb\u30e9\u30a5\u30af\u30b9\u30d8\u30d7\u30f3"
    ],
    "name:lit_x_preferred":[
        "Dorlaukshiobnas"
    ],
    "name:mac_x_preferred":[
        "\u0422\u043e\u0440\u043b\u0430\u0443\u043a\u0441\u0445\u0435\u0431\u043d"
    ],
    "name:may_x_preferred":[
        "\u00deorl\u00e1ksh\u00f6fn"
    ],
    "name:pol_x_preferred":[
        "\u00deorl\u00e1ksh\u00f6fn"
    ],
    "name:rus_x_preferred":[
        "\u0422\u043e\u0440\u043b\u0430\u0443\u043a\u0441\u0445\u0451\u0431\u043d"
    ],
    "name:spa_x_preferred":[
        "\u00deorl\u00e1ksh\u00f6fn"
    ],
    "name:swe_x_preferred":[
        "\u00deorl\u00e1ksh\u00f6fn"
    ],
    "name:tur_x_preferred":[
        "\u00deorl\u00e1ksh\u00f6fn"
    ],
    "name:vol_x_preferred":[
        "\u00deorl\u00e1ksh\u00f6fn"
    ],
    "qs_pg:aaroncc":"IS",
    "qs_pg:gn_country":"IS",
    "qs_pg:gn_fcode":"PPL",
    "qs_pg:gn_pop":1262,
    "qs_pg:name":"Thorlakshofn",
    "qs_pg:name_adm0":"\u00cdsland",
    "qs_pg:name_adm1":"Arnessysla",
    "qs_pg:photos":309,
    "qs_pg:photos_1k":63,
    "qs_pg:photos_9k":1,
    "qs_pg:photos_9r":5,
    "qs_pg:photos_all":309,
    "qs_pg:photos_sr":5,
    "qs_pg:pop_sr":3,
    "qs_pg:qs_pg_placetype":"locality",
    "qs_pg:qs_pg_placetype_gp":"Town",
    "qs_pg:woe_adm0":23424845,
    "woe:adm0_id":23424845,
    "woe:name_adm0":"\u00cdsland",
    "woe:name_adm1":"Arnessysla",
    "woe:placetype":"Town",
    "wof:name":"Thorlakshofn",
    "wof:placetype":"locality",
    "wof:population":1489
},
  "geometry": {"coordinates":[-21.38337,63.85591],"type":"Point"}
}