{
  "type": "Feature",
  "properties": {
    "gn:gn_country":"IS",
    "gn:gn_fcode":"PPL",
    "gn:gn_pop":57,
    "gn:population":57,
    "iso:country":"IS",
    "name:unk_x_variant":[
        "Hallormsta\u00f0ur"
    ],
    "qs_pg:aaroncc":"IS",
    "qs_pg:gn_country":"IS",
    "qs_pg:gn_fcode":"PPL",
    "qs_pg:gn_pop":57,
    "qs_pg:name":"Hallormssta\u00f0ur",
    "qs_pg:photos_9r":0,
    "qs_pg:photos_sr":0,
    "qs_pg:pop_sr":1,
    "qs_pg:qs_pg_placetype":"locality",
    "wof:name":"Hallormssta\u00f0ur",
    "wof:placetype":"locality",
    "wof:population":57
},
  "geometry": {"coordinates":[-14.74186,65.09177],"type":"Point"}
}