{
  "type": "Feature",
  "properties": {
    "iso:country":"IS",
    "name:eng_x_preferred":[
        "Borgir"
    ],
    "name:isl_x_preferred":[
        "Borgir"
    ],
    "wof:name":"Borgir",
    "wof:placetype":"neighbourhood"
},
  "geometry": {"coordinates":[-21.79109677646657,64.15384028206944],"type":"Point"}
}