{
  "type": "Feature",
  "properties": {
    "iso:country":"IS",
    "name:eng_x_preferred":[
        "Sundahofn"
    ],
    "name:isl_x_preferred":[
        "Sundah\u00f6fn"
    ],
    "wof:name":"Sundahofn",
    "wof:placetype":"neighbourhood"
},
  "geometry": {"coordinates":[-21.85678904806141,64.14802507464491],"type":"Point"}
}