{
  "type": "Feature",
  "properties": {
    "iso:country":"IS",
    "name:eng_x_preferred":[
        "Melar"
    ],
    "name:isl_x_preferred":[
        "Melar"
    ],
    "wof:name":"Melar",
    "wof:placetype":"neighbourhood"
},
  "geometry": {"coordinates":[-21.95889629686685,64.14443826866382],"type":"Point"}
}