{
  "type": "Feature",
  "properties": {
    "iso:country":"IS",
    "name:eng_x_preferred":[
        "Austurbaer"
    ],
    "name:isl_x_preferred":[
        "Austurb\u00e6r"
    ],
    "wof:name":"Austurbaer",
    "wof:placetype":"neighbourhood"
},
  "geometry": {"coordinates":[-21.92845499737056,64.14373954558724],"type":"Point"}
}