{
  "type": "Feature",
  "properties": {
    "gn:gn_country":"IS",
    "gn:gn_fcode":"PPL",
    "gn:gn_pop":936,
    "gn:population":813,
    "iso:country":"IS",
    "name:ast_x_preferred":[
        "Bl\u00f6ndu\u00f3sb\u00e6r"
    ],
    "name:bel_x_preferred":[
        "\u0413\u043e\u0440\u0430\u0434 \u0411\u043b\u0451\u043d\u0434\u0443\u043e\u0441"
    ],
    "name:ces_x_preferred":[
        "Bl\u00f6ndu\u00f3s"
    ],
    "name:dan_x_preferred":[
        "Bl\u00f6ndu\u00f3s"
    ],
    "name:deu_x_preferred":[
        "Bl\u00f6ndu\u00f3s"
    ],
    "name:eng_x_preferred":[
        "Blonduos"
    ],
    "name:epo_x_preferred":[
        "Bl\u00f6ndu\u00f3s"
    ],
    "name:eus_x_preferred":[
        "Bl\u00f6ndu\u00f3s"
    ],
    "name:fas_x_preferred":[
        "\u0628\u0644\u0648\u0646\u062f\u0648\u0633"
    ],
    "name:fra_x_preferred":[
        "Bl\u00f6ndu\u00f3s"
    ],
    "name:isl_x_preferred":[
        "Bl\u00f6ndu\u00f3s"
    ],
    "name:isl_x_variant":[
        "Bl\u00f6ndu\u00f3si",
        "Bl\u00f6nd\u00f3s"
    ],
    "name:ita_x_preferred":[
        "Bl\u00f6ndu\u00f3s"
    ],
    "name:jpn_x_preferred":[
        "\u30d6\u30ea\u30e7\u30f3\u30c9\u30a5\u30aa\u30a5\u30b9"
    ],
    "name:kat_x_preferred":[
        "\u10d1\u10da\u10d4\u10dc\u10d3\u10e3\u10dd\u10e3\u10e1\u10d8"
    ],
    "name:kor_x_preferred":[
        "\ube14\ub8b4\ub4a4\uc624\uc2a4"
    ],
    "name:nan_x_preferred":[
        "Bl\u00f6ndu\u00f3sb\u00e6r"
    ],
    "name:nld_x_preferred":[
        "Bl\u00f6ndu\u00f3s"
    ],
    "name:nno_x_preferred":[
        "Bl\u00f6ndu\u00f3s"
    ],
    "name:nob_x_preferred":[
        "Bl\u00f6ndu\u00f3s"
    ],
    "name:nor_x_preferred":[
        "Bl\u00f6ndu\u00f3s"
    ],
    "name:oss_x_preferred":[
        "\u0411\u043b\u0451\u043d\u0434\u044e\u043e\u0443\u0441"
    ],
    "name:pol_x_preferred":[
        "Bl\u00f6ndu\u00f3s"
    ],
    "name:por_x_preferred":[
        "Bl\u00f6ndu\u00f3s"
    ],
    "name:rus_x_preferred":[
        "\u0411\u043b\u0451\u043d\u0434\u044e\u043e\u0443\u0441"
    ],
    "name:sme_x_preferred":[
        "Bl\u00f6ndu\u00f3s"
    ],
    "name:spa_x_preferred":[
        "Bl\u00f6ndu\u00f3sb\u00e6r"
    ],
    "name:sqi_x_preferred":[
        "Bl\u00f6ndu\u00f3s"
    ],
    "name:swe_x_preferred":[
        "Bl\u00f6ndu\u00f3s"
    ],
    "name:unk_x_variant":[
        "Bl\u00f6ndu\u00f3s"
    ],
    "name:vol_x_preferred":[
        "Bl\u00f6ndu\u00f3s"
    ],
    "name:zho_x_preferred":[
        "\u5e03\u502b\u8fea\u6b50\u65af"
    ],
    "qs_pg:aaroncc":"IS",
    "qs_pg:gn_country":"IS",
    "qs_pg:gn_fcode":"PPL",
    "qs_pg:gn_pop":936,
    "qs_pg:name":"Blonduos",
    "qs_pg:name_adm0":"\u00cdsland",
    "qs_pg:name_adm1":"Austur-Hunavatnssysla",
    "qs_pg:photos":295,
    "qs_pg:photos_1k":60,
    "qs_pg:photos_9k":1,
    "qs_pg:photos_9r":4,
    "qs_pg:photos_all":295,
    "qs_pg:photos_sr":5,
    "qs_pg:pop_sr":2,
    "qs_pg:qs_pg_placetype":"locality",
    "qs_pg:qs_pg_placetype_gp":"Town",
    "qs_pg:woe_adm0":23424845,
    "woe:adm0_id":23424845,
    "woe:name_adm0":"\u00cdsland",
    "woe:name_adm1":"Austur-Hunavatnssysla",
    "woe:placetype":"Town",
    "wof:name":"Blonduos",
    "wof:placetype":"locality",
    "wof:population":813
},
  "geometry": {"coordinates":[-20.29001,65.65693],"type":"Point"}
}