{
  "type": "Feature",
  "properties": {
    "gn:population":251,
    "iso:country":"IS",
    "name:deu_x_preferred":[
        "Borgarbygg\u00f0"
    ],
    "name:eus_x_preferred":[
        "Borgarbygg\u00f0"
    ],
    "name:fra_x_preferred":[
        "Borgarbygg\u00f0"
    ],
    "name:isl_x_preferred":[
        "Borgarbygg\u00f0"
    ],
    "name:isl_x_variant":[
        "Hvanneyri",
        "Hvanneyrar"
    ],
    "name:ita_x_preferred":[
        "Borgarbygg\u00f0"
    ],
    "name:nld_x_preferred":[
        "Borgarbygg\u00f0"
    ],
    "name:nor_x_preferred":[
        "Borgarbygg\u00f0"
    ],
    "name:rus_x_preferred":[
        "\u0411\u043e\u0440\u0433\u0430\u0440\u0431\u0438\u0433\u0434"
    ],
    "name:sme_x_preferred":[
        "Borgarbygg\u00f0"
    ],
    "name:spa_x_preferred":[
        "Borgarbygg\u00f0"
    ],
    "qs:a0":"\u00cdsland",
    "qs:a1":"*",
    "qs:a1r":"0",
    "qs:adm0":"\u00cdsland",
    "qs:la_lc":"*",
    "qs:level":"locality",
    "qs:loc":"Hvanneyri",
    "qs:loc_alt":"Hvanneyri",
    "qs:pop":0,
    "qs:type":"buffered point",
    "wof:name":"Hvanneyri",
    "wof:placetype":"locality",
    "wof:population":251
},
  "geometry": {"coordinates":[-21.747858,64.5652],"type":"Point"}
}