{
  "type": "Feature",
  "properties": {
    "iso:country":"IS",
    "qs_pg:aaroncc":"IS",
    "qs_pg:name":"Eskifj\u00f6r\u00ffur",
    "qs_pg:name_adm0":"\u00cdsland",
    "qs_pg:name_adm1":"Sudur-Mulasysla",
    "qs_pg:photos":158,
    "qs_pg:photos_1k":32,
    "qs_pg:photos_9k":1,
    "qs_pg:photos_9r":4,
    "qs_pg:photos_all":158,
    "qs_pg:photos_sr":4,
    "qs_pg:pop_sr":0,
    "qs_pg:qs_pg_placetype":"locality",
    "qs_pg:qs_pg_placetype_gp":"Town",
    "qs_pg:woe_adm0":23424845,
    "woe:adm0_id":23424845,
    "woe:name_adm0":"\u00cdsland",
    "woe:name_adm1":"Sudur-Mulasysla",
    "woe:placetype":"Town",
    "wof:name":"Eskifj\u00f6r\u00ffur",
    "wof:placetype":"locality"
},
  "geometry": {"coordinates":[-13.9333675,65.06011650000001],"type":"Point"}
}