{
  "type": "Feature",
  "properties": {
    "iso:country":"IS",
    "name:eng_x_preferred":[
        "Holar"
    ],
    "name:isl_x_preferred":[
        "H\u00f3lar"
    ],
    "wof:name":"Holar",
    "wof:placetype":"neighbourhood"
},
  "geometry": {"coordinates":[-21.8139277510888,64.10997618647235],"type":"Point"}
}