{
  "type": "Feature",
  "properties": {
    "iso:country":"IS",
    "name:eng_x_preferred":[
        "Hlemmur"
    ],
    "name:isl_x_preferred":[
        "Hlemmur"
    ],
    "wof:name":"Hlemmur",
    "wof:placetype":"neighbourhood"
},
  "geometry": {"coordinates":[-21.91277658372021,64.14232956869988],"type":"Point"}
}