{
  "type": "Feature",
  "properties": {
    "iso:country":"IS",
    "name:eng_x_preferred":[
        "Grafarvogur"
    ],
    "name:isl_x_preferred":[
        "Grafarvogur"
    ],
    "wof:name":"Grafarvogur",
    "wof:placetype":"neighbourhood"
},
  "geometry": {"coordinates":[-21.7912684379299,64.1414395394536],"type":"Point"}
}