{
  "type": "Feature",
  "properties": {
    "gn:country":"IS",
    "gn:fcode":"PPL",
    "gn:population":2281,
    "iso:country":"IS",
    "name:deu_x_preferred":[
        "Hverager\u00f0i"
    ],
    "name:eng_x_preferred":[
        "Hveragerdi"
    ],
    "name:eng_x_variant":[
        "Hverager\u00f0i"
    ],
    "name:fra_x_preferred":[
        "Hverager\u00f0i"
    ],
    "name:isl_x_preferred":[
        "Hverager\u00f0isb\u00e6r"
    ],
    "name:isl_x_variant":[
        "Hverager\u00f0i",
        "Hverager\u00f0is"
    ],
    "name:ita_x_preferred":[
        "Hverager\u00f0i"
    ],
    "name:jpn_x_preferred":[
        "\u30af\u30d9\u30e9\u30b2\u30eb\u30b8"
    ],
    "name:jpn_x_variant":[
        "\u30af\u30f4\u30a7\u30e9\u30b2\u30eb\u30b8"
    ],
    "name:nld_x_preferred":[
        "Hverager\u00f0i"
    ],
    "name:pol_x_preferred":[
        "Hverager\u00f0i"
    ],
    "qs_pg:aaroncc":"IS",
    "qs_pg:gn_country":"IS",
    "qs_pg:gn_fcode":"PPL",
    "qs_pg:gn_pop":2281,
    "qs_pg:name":"Hveragerdhi",
    "qs_pg:name_adm0":"\u00cdsland",
    "qs_pg:name_adm1":"Arnessysla",
    "qs_pg:photos":1862,
    "qs_pg:photos_1k":377,
    "qs_pg:photos_9k":8,
    "qs_pg:photos_9r":9,
    "qs_pg:photos_all":1862,
    "qs_pg:photos_sr":15,
    "qs_pg:pop_sr":4,
    "qs_pg:qs_pg_placetype":"locality",
    "qs_pg:qs_pg_placetype_gp":"Town",
    "qs_pg:woe_adm0":23424845,
    "woe:adm0_id":23424845,
    "woe:name_adm0":"\u00cdsland",
    "woe:name_adm1":"Arnessysla",
    "woe:placetype":"Town",
    "wof:name":"Hveragerdhi",
    "wof:placetype":"locality",
    "wof:population":2288
},
  "geometry": {"coordinates":[-21.2034,64.00411],"type":"Point"}
}