{
  "type": "Feature",
  "properties": {
    "gn:admin1_code":"42.0",
    "gn:admin2_code":"8613",
    "gn:asciiname":"Asolfsskali",
    "gn:country_code":"IS",
    "gn:dem":105,
    "gn:feature_class":"P",
    "gn:feature_code":"PPL",
    "gn:name":"\u00c1s\u00f3lfssk\u00e1li",
    "gn:population":0,
    "gn:timezone":"Atlantic/Reykjavik",
    "iso:country":"IS",
    "wof:name":"Asolfsskali",
    "wof:placetype":"locality"
},
  "geometry": {"coordinates":[-19.79964,63.57301],"type":"Point"}
}