{
  "type": "Feature",
  "properties": {
    "gn:gn_country":"IS",
    "gn:gn_fcode":"PPL",
    "gn:gn_pop":0,
    "iso:country":"IS",
    "name:unk_x_variant":[
        "Strandakirkja"
    ],
    "qs_pg:aaroncc":"IS",
    "qs_pg:gn_country":"IS",
    "qs_pg:gn_fcode":"PPL",
    "qs_pg:gn_pop":0,
    "qs_pg:name":"Strandarkirkja",
    "qs_pg:name_adm0":"\u00cdsland",
    "qs_pg:name_adm1":"Arnessysla",
    "qs_pg:photos":257,
    "qs_pg:photos_1k":52,
    "qs_pg:photos_9k":1,
    "qs_pg:photos_9r":4,
    "qs_pg:photos_all":257,
    "qs_pg:photos_sr":5,
    "qs_pg:pop_sr":0,
    "qs_pg:qs_pg_placetype":"locality",
    "qs_pg:qs_pg_placetype_gp":"Town",
    "qs_pg:woe_adm0":23424845,
    "woe:adm0_id":23424845,
    "woe:name_adm0":"\u00cdsland",
    "woe:name_adm1":"Arnessysla",
    "woe:placetype":"Town",
    "wof:name":"Strandarkirkja",
    "wof:placetype":"locality"
},
  "geometry": {"coordinates":[-21.70477,63.83593],"type":"Point"}
}